compas_framework/__init__.py
compas_framework-0.1.3.dist-info/licenses/LICENSE
compas_framework-0.1.3.dist-info/METADATA
compas_framework-0.1.3.dist-info/WHEEL
compas_framework-0.1.3.dist-info/top_level.txt
compas_framework-0.1.3.dist-info/RECORD
