Metadata-Version: 2.4
Name: compas_framework
Version: 0.1.3
Summary: The COMPAS framework packages
Author-email: tom van mele <tom.v.mele@gmail.com>
License: MIT License
Project-URL: Homepage, https://compas-dev.github.io/compas_framework
Project-URL: Documentation, https://compas-dev.github.io/compas_framework
Project-URL: Repository, https://github.com/compas-dev/compas_framework
Project-URL: Changelog, https://github.com/compas-dev/compas_framework/blob/main/CHANGELOG.md
Project-URL: Issues, https://github.com/compas-dev/compas_framework/issues
Project-URL: Forum, https://forum.compas-framework.org/
Classifier: Development Status :: 4 - Beta
Classifier: Topic :: Scientific/Engineering
Classifier: Operating System :: Unix
Classifier: Operating System :: POSIX
Classifier: Operating System :: Microsoft :: Windows
Classifier: Programming Language :: Python
Classifier: Programming Language :: Python :: 3
Classifier: Programming Language :: Python :: 3.10
Classifier: Programming Language :: Python :: 3.11
Classifier: Programming Language :: Python :: 3.12
Requires-Python: >=3.9
License-File: LICENSE
Requires-Dist: compas>=2.13
Requires-Dist: compas_cgal
Requires-Dist: compas_gmsh
Requires-Dist: compas_libigl
Requires-Dist: compas_model
Requires-Dist: compas_session
Requires-Dist: compas_shapeop
Requires-Dist: compas_viewer
Provides-Extra: dev
Requires-Dist: attrs>=17.4; extra == "dev"
Requires-Dist: black>=22.12.0; extra == "dev"
Requires-Dist: bump-my-version; extra == "dev"
Requires-Dist: compas_invocations2; extra == "dev"
Requires-Dist: invoke>=0.14; extra == "dev"
Requires-Dist: ruff; extra == "dev"
Requires-Dist: sphinx_compas2_theme; extra == "dev"
Requires-Dist: twine; extra == "dev"
Requires-Dist: wheel; extra == "dev"
Provides-Extra: notebook
Requires-Dist: compas_notebook; extra == "notebook"
Dynamic: license-file
